README.md
goeyewitnesscategorizer.py
goeyewitnesscategorizer-0.1.2.dist-info/METADATA
goeyewitnesscategorizer-0.1.2.dist-info/WHEEL
goeyewitnesscategorizer-0.1.2.dist-info/entry_points.txt
goeyewitnesscategorizer-0.1.2.dist-info/RECORD
