Metadata-Version: 2.4
Name: goeyewitnesscategorizer
Version: 0.1.2
Summary: Parse GoWitness SQLite results and categorize HTML using EyeWitness-style signatures to produce a CSV report.
Project-URL: Homepage, https://github.com/DefensiveOrigins/goeyewitnesscategorizer
Project-URL: Source, https://github.com/DefensiveOrigins/goeyewitnesscategorizer
Project-URL: Issues, https://github.com/DefensiveOrigins/goeyewitnesscategorizer/issues
Author-email: Defensive Origins <info@defensiveorigins.com>
Keywords: categorization,eyewitness,gowitness,reconnaissance,security,web
Classifier: Environment :: Console
Classifier: Intended Audience :: Information Technology
Classifier: Intended Audience :: System Administrators
Classifier: License :: OSI Approved :: MIT License
Classifier: Programming Language :: Python :: 3
Classifier: Programming Language :: Python :: 3 :: Only
Classifier: Programming Language :: Python :: 3.8
Classifier: Programming Language :: Python :: 3.9
Classifier: Programming Language :: Python :: 3.10
Classifier: Programming Language :: Python :: 3.11
Classifier: Programming Language :: Python :: 3.12
Classifier: Topic :: Internet :: WWW/HTTP
Classifier: Topic :: Security
Requires-Python: >=3.8
Requires-Dist: pandas>=1.0
